pydddantic/__init__.py
pydddantic/aes/__init__.py
pydddantic/aes/aggregate.py
pydddantic/aes/store.py
pydddantic/aes/stream.py
pydddantic/aggregate_root.py
pydddantic/eda/__init__.py
pydddantic/eda/command.py
pydddantic/eda/event.py
pydddantic/eda/message.py
pydddantic/eda/message_bus.py
pydddantic/eda/subscriber.py
pydddantic/entity.py
pydddantic/immutable_entity.py
pydddantic/unique_id.py
pydddantic/value.py
pydddantic/value_object.py
pydddantic-0.2.0.dist-info/LICENSE
pydddantic-0.2.0.dist-info/METADATA
pydddantic-0.2.0.dist-info/WHEEL
pydddantic-0.2.0.dist-info/RECORD
