Metadata-Version: 2.3
Name: pydddantic
Version: 0.2.0
Summary: A Pydantic-Based Domain-Driven Design Framework
License: MIT
Keywords: pydantic,domain-driven design,ddd,framework
Author: Dave Sutherland
Author-email: dave@daveography.ca
Requires-Python: >=3.10
Classifier: License :: OSI Approved :: MIT License
Classifier: Programming Language :: Python :: 3
Classifier: Programming Language :: Python :: 3.10
Classifier: Programming Language :: Python :: 3.11
Classifier: Programming Language :: Python :: 3.12
Classifier: Programming Language :: Python :: 3.13
Requires-Dist: pydantic (>=2.10.0)
Project-URL: Repository, https://github.com/Daveography/pydddantic
